{
  "_embedded": {
    "tournamentEntities": [
      {
        "id": 1,
        "playersNumber": 12,
        "tournamentDescription": "Free For All",
        "tournamentMode": "FFA",
        "adminId": 100,
        "_links": {
          "self": {
            "href": "http://localhost:8080/tournament/1"
          },
          "tournamentEntity": {
            "href": "http://localhost:8080/tournament/1"
          },
          "game": {
            "href": "http://localhost:8080/tournament/1/game"
          }
        }
      },
      {
        "id": 1,
        "playersNumber": 12,
        "tournamentDescription": "Free For All",
        "tournamentMode": "FFA",
        "adminId": 100,
        "_links": {
          "self": {
            "href": "http://localhost:8080/tournament/1"
          },
          "tournamentEntity": {
            "href": "http://localhost:8080/tournament/1"
          },
          "game": {
            "href": "http://localhost:8080/tournament/1/game"
          }
        }
      },
      {
        "id": 1,
        "playersNumber": 12,
        "tournamentDescription": "Free For All",
        "tournamentMode": "FFA",
        "adminId": 100,
        "_links": {
          "self": {
            "href": "http://localhost:8080/tournament/1"
          },
          "tournamentEntity": {
            "href": "http://localhost:8080/tournament/1"
          },
          "game": {
            "href": "http://localhost:8080/tournament/1/game"
          }
        }
      },
      {
        "id": 2,
        "playersNumber": 18,
        "tournamentDescription": "Search and Destroy",
        "tournamentMode": "SnD",
        "adminId": 101,
        "_links": {
          "self": {
            "href": "http://localhost:8080/tournament/2"
          },
          "tournamentEntity": {
            "href": "http://localhost:8080/tournament/2"
          },
          "game": {
            "href": "http://localhost:8080/tournament/2/game"
          }
        }
      },
      {
        "id": 2,
        "playersNumber": 18,
        "tournamentDescription": "Search and Destroy",
        "tournamentMode": "SnD",
        "adminId": 101,
        "_links": {
          "self": {
            "href": "http://localhost:8080/tournament/2"
          },
          "tournamentEntity": {
            "href": "http://localhost:8080/tournament/2"
          },
          "game": {
            "href": "http://localhost:8080/tournament/2/game"
          }
        }
      },
      {
        "id": 2,
        "playersNumber": 18,
        "tournamentDescription": "Search and Destroy",
        "tournamentMode": "SnD",
        "adminId": 101,
        "_links": {
          "self": {
            "href": "http://localhost:8080/tournament/2"
          },
          "tournamentEntity": {
            "href": "http://localhost:8080/tournament/2"
          },
          "game": {
            "href": "http://localhost:8080/tournament/2/game"
          }
        }
      }
    ]
  },
  "_links": {
    "self": {
      "href": "http://localhost:8080/tournament{?page,size,sort}",
      "templated": true
    },
    "profile": {
      "href": "http://localhost:8080/profile/tournament"
    },
    "search": {
      "href": "http://localhost:8080/tournament/search"
    }
  },
  "page": {
    "size": 20,
    "totalElements": 2,
    "totalPages": 1,
    "number": 0
  }
}